{"zonas":[{"code":"001","id":229,"desc":"?NICA"}],"tipo":"RV","tarifa":3, "code":"106120","descrip":"EDIFICIO TRIPLANTA FISCALÍ PROVINCIAL","suministrosBajo":[{"precio":85.76,"tipo":"1","code":"4782041111","descrip":"BARANDA DE HIERRO TIPO BHRA-12","pertenece":"R266 ","um":"m","id":22619},{"precio":884.19,"tipo":"1","code":"4483990101","descrip":"CELOSIA HORMIGON (MORTERO) CUADRADA GRADO A 200X200X100","pertenece":"R266 ","um":"mu","id":22305},{"precio":22.54,"tipo":"1","code":"3748909051","descrip":"TUBO PVC SANITARIO 110 MM (4\")","pertenece":"R266 ","um":"m","id":21577},{"precio":5.03,"tipo":"1","code":"3161098112","descrip":"ELECTRODOS PARA SOLDAR ACERO DULCE E-6011 DE 3 MM","pertenece":"R266 ","um":"kg","id":21155},{"precio":243.53,"tipo":"1","code":"4783029200","descrip":"VENTANA ALUM CON PERS ALUM FIJA O MOV NO NORMALIZADA","pertenece":"R266 ","um":"m2","id":22627},{"precio":1.66,"tipo":"1","code":"3745050261","descrip":"CONECTOR PLASTICO E1 PARA TUBERIA ELECTRICA DE 3\/4\"","pertenece":"R266 ","um":"u","id":21552},{"precio":723.41,"tipo":"S","code":"0002204022","descrip":"MORTERO 1:4:1 DE CEMENTO PP-250, ARENA E HIDRATO DE CAL (5.2 Mpa) (MANUAL)","pertenece":"R266 ","um":"m3","id":330},{"precio":1720.71,"tipo":"1","code":"4491010710","descrip":"AZULEJO AZUL MEDIO DE 200X200X7 MM","pertenece":"R266 ","um":"mu","id":22321},{"precio":0.43,"tipo":"1","code":"2708561003","descrip":"TUERCA ELECTRICA GALVANIZADA DE 3\/4\"","pertenece":"R266 ","um":"u","id":20222},{"precio":2.26,"tipo":"1","code":"2708994035","descrip":"CAJA ELECTRICA CHAPA 4X4X3\/4\"","pertenece":"R266 ","um":"u","id":20234},{"precio":6064.45,"tipo":"1","code":"3199999999","descrip":"COMPLEJIDAD II OTRAS PARTES NO INTEG. ESTRUC. BASICA","pertenece":"R266 ","um":"t","id":21243},{"precio":1.96,"tipo":"1","code":"6798082101","descrip":"INTERRUPTOR INCRUSTAR S\/P 10A 300 V C\/PLACA","pertenece":"R266 ","um":"u","id":23052},{"precio":11.45,"tipo":"1","code":"3032012253","descrip":"TORNILLO ROSCA MADERA DE 2 1\/2\" # 9","pertenece":"R266 ","um":"gr","id":20650},{"precio":100.27,"tipo":"1","code":"4481060012","descrip":"BALDOSAS DE TERRAZZO 300X300X30MM CEM.BLANCO C\\PIGMENTO","pertenece":"R266 ","um":"m2","id":22289},{"precio":1465.98,"tipo":"1","code":"4401010011","descrip":"CEMENTO GRIS PP-250 A GRANEL","pertenece":"R266 ","um":"t","id":22060},{"precio":8.37,"tipo":"1","code":"3031451009","descrip":"ARANDELAS PLANAS DE HIERRO DE 1\/2\"","pertenece":"R266 ","um":"kg","id":20616},{"precio":12.97,"tipo":"1","code":"3999411313","descrip":"MASILLA HIERRO Y CRISTAL LINEA 4-M-1 ENVASE 4 LT","pertenece":"R266 ","um":"gl","id":22003},{"precio":1043.34,"tipo":"S","code":"0002204131","descrip":"MORTERO DE CEMENTO Y ARENA 1:3  10% HIDRATO DE CAL .  MANUAL","pertenece":"R266 ","um":"m3","id":351},{"precio":3045.99,"tipo":"1","code":"2723620000","descrip":"ANGULAR DE ACERO ALAS IGUALES GRADO ST-3KP","pertenece":"R266 ","um":"t","id":20300},{"precio":0.82,"tipo":"1","code":"2708576310","descrip":"TAPA CAJA ELECT DE 4X4\" REDONDA CENTRO 52-C3 AC NEGRO","pertenece":"R266 ","um":"u","id":20231},{"precio":906.16,"tipo":"S","code":"0002204132","descrip":"MORTERO DE CEMENTO Y ARENA 1:4  10% HIDRATO DE CAL .  MANUAL","pertenece":"R266 ","um":"m3","id":352},{"precio":1335.19,"tipo":"S","code":"0002204122","descrip":"MORTERO DE CEMENTO Y ARENA 1:2 .  MANUAL","pertenece":"R266 ","um":"m3","id":346},{"precio":20469.36,"tipo":"1","code":"4572990001","descrip":"PEGAFAL EN TAMBORES DE 55 GALONES","pertenece":"R266 ","um":"bi","id":22486},{"precio":17.58,"tipo":"1","code":"4414990001","descrip":"ROCOSO MATERIAL DE RELLENO  (CIUDAD DE LA HABANA)","pertenece":"R266 ","um":"m3","id":22112},{"precio":0.43,"tipo":"1","code":"3037111071","descrip":"EXPANSION DE PLOMO TORNILLO ROSCA MADERA 3\/8X1 1\/2\"","pertenece":"R266 ","um":"u","id":20796},{"precio":714.57,"tipo":"S","code":"0002204344","descrip":"HORMIGON 200KG\/CM2 100% GRAVIL.HECHO OBRA C\\HOR.ESTAC.","pertenece":"R266 ","um":"m3","id":389},{"precio":1020.2,"tipo":"S","code":"0002204123","descrip":"MORTERO DE CEMENTO Y ARENA 1:3 .  MANUAL","pertenece":"R266 ","um":"m3","id":347},{"precio":10.04,"tipo":"1","code":"3748929221","descrip":"TUBERIA PLASTICA HIDRAULICA DE 20 MM DE DIAMETRO","pertenece":"R266 ","um":"m","id":21669},{"precio":13.71,"tipo":"1","code":"3034401005","descrip":"ARANDELA DE PRESION DE ACERO DE 1\/4\"","pertenece":"R266 ","um":"mu","id":20682},{"precio":40.57,"tipo":"1","code":"4579010111","descrip":"MANTA IMPERMEABILIZANTE SOPREMA O ICA","pertenece":"R266 ","um":"m2","id":22498},{"precio":3580.51,"tipo":"1","code":"4472010002","descrip":"BLOQUE HORM BAS\/GRANITO-ARENA-C\/GRIS 400 X150 X 200 MM","pertenece":"R266 ","um":"mu","id":22228},{"precio":473.92,"tipo":"1","code":"4783019000","descrip":"PUERTA DE ALUM Y VIDRIO NO NORMALIZADA","pertenece":"R266 ","um":"m2","id":22624},{"precio":7.07,"tipo":"1","code":"3037131071","descrip":"EXPANSION DE PLOMO PARA TORNILLO MAQUINA 3\/8X1 1\/2\"","pertenece":"R266 ","um":"u","id":20800},{"precio":2.76,"tipo":"1","code":"3745010401","descrip":"TUBERIA PLASTICA ELECTRICA E1 DE 1\/2\"","pertenece":"R266 ","um":"m","id":21530},{"precio":9.96,"tipo":"1","code":"3031451005","descrip":"ARANDELAS PLANAS DE HIERRO DE 1\/4\"","pertenece":"R266 ","um":"kg","id":20614},{"precio":2431.12,"tipo":"1","code":"4472010001","descrip":"BLOQUE HORM BAS\/GRANITO-ARENA-C\/GRIS 400 X 100 X 200 MM","pertenece":"R266 ","um":"mu","id":22227},{"precio":1547.78,"tipo":"1","code":"4542010001","descrip":"LADR BARRO MACIZO NO REFRAC CORRIENTE 250 X 120 X 65 MM","pertenece":"R266 ","um":"mu","id":22414},{"precio":3.56,"tipo":"1","code":"2708993001","descrip":"PATA DE CABRA DE 3\/8\" DE INCRUSTAR","pertenece":"R266 ","um":"u","id":20233},{"precio":27.29,"tipo":"1","code":"4421030001","descrip":"ARENA DE MINAS BENEFICIADA Y CERNIDA GRADO A","pertenece":"R266 ","um":"m3","id":22120},{"precio":18.42,"tipo":"1","code":"3035015061","descrip":"TORNILLO ACERO PULIDO CAB\/TCA HEXAG R\/G 1\/4X1 1\/4\"","pertenece":"R266 ","um":"cu","id":20708},{"precio":14.31,"tipo":"1","code":"3748909022","descrip":"TUBO PVC SANITARIO 63 MM (2 1\/2\")","pertenece":"R266 ","um":"m","id":21570},{"precio":169.32,"tipo":"1","code":"4402010102","descrip":"CEMENTO BLANCO EN BOLSAS DE 50 KG","pertenece":"R266 ","um":"bs","id":22076},{"precio":10.29,"tipo":"1","code":"4562030001","descrip":"VIDRIO PLANO LISO TRANSPARENTE 3 MM 40\"X40\"","pertenece":"R266 ","um":"m2","id":22466},{"precio":13.56,"tipo":"1","code":"3035015057","descrip":"TORNILLO ACERO PULIDO CAB\/TCA HEXAG R\/G 1\/4X3\/4\"","pertenece":"R266 ","um":"cu","id":20706},{"precio":0.55,"tipo":"1","code":"6791011002","descrip":"TAPE FRICCION ROLLO DE 10 YARDAS DE 3\/4\"","pertenece":"R266 ","um":"ro","id":23025},{"precio":2.51,"tipo":"1","code":"6798062202","descrip":"TOMACORRIENTE DOBLE DE INCRUSTAR 2P 15A 125 V","pertenece":"R266 ","um":"u","id":23039},{"precio":2.81,"tipo":"1","code":"3748929201","descrip":"TUBERIA PLASTICA HIDRAULICA DE 12 MM DE DIAMETRO","pertenece":"R266 ","um":"m","id":21666},{"precio":2.65,"tipo":"1","code":"2615100160","descrip":"ALAMBRE LISO DE ACERO GALVANIZADO 1.6 MM CALIBRE 16","pertenece":"R266 ","um":"kg","id":19763},{"precio":84.77,"tipo":"1","code":"4401010012","descrip":"CEMENTO GRIS PP-250 EN BOLSA DE 50 KG","pertenece":"R266 ","um":"bs","id":22061},{"precio":52.57,"tipo":"1","code":"3034401009","descrip":"ARANDELA DE PRESION DE ACERO DE 1\/2\"","pertenece":"R266 ","um":"mu","id":20684},{"precio":5.03,"tipo":"1","code":"3161098116","descrip":"ELECTRODOS PARA SOLDAR ACERO DULCE E-6011 DE 4 MM","pertenece":"R266 ","um":"kg","id":21156},{"precio":3.46,"tipo":"1","code":"3745010411","descrip":"TUBERIA PLASTICA ELECTRICA E1 DE 3\/4\"","pertenece":"R266 ","um":"m","id":21531},{"precio":285.18,"tipo":"1","code":"3035015298","descrip":"TORNILLO MAQ ACERO PULIDO CAB\/TCA HEXAG R\/G 1\/2X12\"","pertenece":"R266 ","um":"cu","id":20733},{"precio":40.08,"tipo":"1","code":"5282991120","descrip":"LAMPARA COMERCIAL 1X20 WATT ADOSADA","pertenece":"R266 ","um":"u","id":22750},{"precio":162.15,"tipo":"1","code":"3199620111","descrip":"TAPA DE SALIDA DE AZOTEA","pertenece":"R266 ","um":"u","id":21189},{"precio":21.07,"tipo":"1","code":"3034163026","descrip":"TUERCA HEXAGONAL ACERO PULIDO DE 1\/4\" ROSCA GRUESA","pertenece":"R266 ","um":"cu","id":20664},{"precio":13.75,"tipo":"1","code":"3748909041","descrip":"TUBERIA PLASTICA DE 100 MM (4\") X 2.1 ESP (LIGERO)","pertenece":"R266 ","um":"m","id":21576},{"precio":0.34,"tipo":"1","code":"6763120830","descrip":"CABLE C\/AISL PVC O GOMA MONOCOND. 1.5-4 MM2","pertenece":"R266 ","um":"m","id":22917},{"precio":2.33,"tipo":"1","code":"2725993675","descrip":"PLANCHUELA DE ACERO GRADO ST-3KP LIGERA DE 50X3 MM","pertenece":"R266 ","um":"m","id":20347}],"inversionista":"09226","salario":3,"grupos":[],"renglones":[{"conMat":"0 ","cantRv":0.08,"uoId":4831,"salariomn":2.30803584,"rvId":"042726","costEquip":0.6935306400000001,"costMat":0.0,"costMano":2.51788152},{"conMat":"1 ","cantRv":0.0045,"uoId":4831,"salariomn":0.380151,"rvId":"301303","costEquip":0.0,"costMat":76.7564343,"costMano":0.4146884999999999},{"conMat":"1 ","cantRv":0.0045,"uoId":4831,"salariomn":1.1081504519999998,"rvId":"305351","costEquip":0.0,"costMat":0.2775708,"costMano":1.208850876},{"conMat":"0 ","cantRv":1.02,"uoId":4829,"salariomn":34.67592,"rvId":"042424","costEquip":10.612080000000002,"costMat":0.0,"costMano":37.82976},{"conMat":"1 ","cantRv":0.0249,"uoId":4829,"salariomn":15.844866,"rvId":"301102","costEquip":0.0,"costMat":424.71893646,"costMano":17.2833141},{"conMat":"1 ","cantRv":0.0381,"uoId":4829,"salariomn":3.2186118000000006,"rvId":"301303","costEquip":0.0,"costMat":649.8711437400001,"costMano":3.5110292999999997},{"conMat":"1 ","cantRv":0.0099,"uoId":4829,"salariomn":3.5020656000000008,"rvId":"301401","costEquip":0.0,"costMat":168.86415546000003,"costMano":3.8200239000000002},{"conMat":"1 ","cantRv":0.0249,"uoId":4829,"salariomn":32.010286034399996,"rvId":"305112","costEquip":0.0,"costMat":0.6947099999999999,"costMano":34.9161128472},{"conMat":"1 ","cantRv":0.048,"uoId":4829,"salariomn":7.998192000000001,"rvId":"305321","costEquip":0.0,"costMat":2.1952512,"costMano":8.725007999999999},{"conMat":"1 ","cantRv":10.2,"uoId":4829,"salariomn":234.44551079999997,"rvId":"311521","costEquip":0.0,"costMat":211.90091999999999,"costMano":255.7501692},{"conMat":"1 ","cantRv":69.6,"uoId":4855,"salariomn":444.9926112,"rvId":"131101","costEquip":0.0,"costMat":755.2400399999998,"costMano":485.4776088},{"conMat":"1 ","cantRv":69.6,"uoId":4855,"salariomn":137.3208,"rvId":"131142","costEquip":0.0,"costMat":464.64612,"costMano":149.81400000000002},{"conMat":"1 ","cantRv":69.6,"uoId":4855,"salariomn":400.4903711999999,"rvId":"131201","costEquip":0.0,"costMat":387.68988719999993,"costMano":436.9265976},{"conMat":"0 ","cantRv":2.8,"uoId":4855,"salariomn":81.60306,"rvId":"132331","costEquip":0.0,"costMat":0.0,"costMano":89.02733839999999},{"conMat":"0 ","cantRv":19.3,"uoId":4855,"salariomn":393.71999999999997,"rvId":"132332","costEquip":0.0,"costMat":0.0,"costMano":429.54080000000005},{"conMat":"0 ","cantRv":2.8,"uoId":4856,"salariomn":29.3972336,"rvId":"112978","costEquip":0.0,"costMat":0.0,"costMano":32.071788},{"conMat":"0 ","cantRv":1.7,"uoId":4828,"salariomn":72.24149999999999,"rvId":"042125","costEquip":22.1085,"costMat":0.0,"costMano":78.812},{"conMat":"1 ","cantRv":0.03638,"uoId":4828,"salariomn":23.1500492,"rvId":"301102","costEquip":0.0,"costMat":620.5331288520001,"costMano":25.251685420000005},{"conMat":"1 ","cantRv":0.08151,"uoId":4828,"salariomn":17.64243195,"rvId":"301402","costEquip":0.0,"costMat":1390.3148799540002,"costMano":19.244429489999998},{"conMat":"1 ","cantRv":0.03638,"uoId":4828,"salariomn":46.768442005279994,"rvId":"305117","costEquip":0.0,"costMat":1.015002,"costMano":51.013983348640004},{"conMat":"1 ","cantRv":0.03549,"uoId":4828,"salariomn":5.913663210000001,"rvId":"305323","costEquip":0.0,"costMat":1.623113856,"costMano":6.451052789999999},{"conMat":"1 ","cantRv":20.3,"uoId":4828,"salariomn":287.06396459999996,"rvId":"311311","costEquip":0.0,"costMat":738.3739300000001,"costMano":313.1501954},{"conMat":"0 ","cantRv":10.0,"uoId":4826,"salariomn":261.42924,"rvId":"044324","costEquip":40.00338,"costMat":0.0,"costMano":285.20672},{"conMat":"1 ","cantRv":0.00375,"uoId":4826,"salariomn":2.386275,"rvId":"301102","costEquip":0.0,"costMat":63.96369525,"costMano":2.60290875},{"conMat":"1 ","cantRv":0.58416,"uoId":4826,"salariomn":49.34866848000001,"rvId":"301303","costEquip":0.0,"costMat":9964.008591264,"costMano":53.83209648},{"conMat":"1 ","cantRv":0.02083,"uoId":4826,"salariomn":7.368487520000001,"rvId":"301401","costEquip":0.0,"costMat":355.29700588200006,"costMano":8.03748463},{"conMat":"1 ","cantRv":0.17878,"uoId":4826,"salariomn":38.6960371,"rvId":"301402","costEquip":0.0,"costMat":3049.447849812,"costMano":42.209779219999994},{"conMat":"1 ","cantRv":0.78381,"uoId":4826,"salariomn":243.70036794936,"rvId":"305361","costEquip":0.0,"costMat":48.347281944,"costMano":265.84603536168},{"conMat":"1 ","cantRv":9.69,"uoId":4826,"salariomn":26.7499233,"rvId":"311711","costEquip":0.0,"costMat":20.130587399999996,"costMano":29.180756699999996},{"conMat":"1 ","cantRv":103.2,"uoId":4850,"salariomn":397.10844000000003,"rvId":"131811","costEquip":0.0,"costMat":55.1166432,"costMano":433.23752160000004},{"conMat":"1 ","cantRv":15.4,"uoId":4850,"salariomn":32.854206,"rvId":"131821","costEquip":0.0,"costMat":24.6743112,"costMano":35.8432228},{"conMat":"1 ","cantRv":66.6,"uoId":4850,"salariomn":166.88028599999998,"rvId":"131831","costEquip":0.0,"costMat":106.70838479999999,"costMano":182.06275499999998},{"conMat":"0 ","cantRv":109.5,"uoId":4825,"salariomn":2021.8079999999998,"rvId":"012131","costEquip":12604.561425,"costMat":0.0,"costMano":2205.768},{"conMat":"0 ","cantRv":33.74,"uoId":4825,"salariomn":1029.4667824,"rvId":"014211","costEquip":459.316116,"costMat":0.0,"costMano":1123.1357704},{"conMat":"0 ","cantRv":1.08,"uoId":4825,"salariomn":0.0,"rvId":"016141","costEquip":922.6465056000002,"costMat":0.0,"costMano":0.0},{"conMat":"0 ","cantRv":10.83368,"uoId":4825,"salariomn":0.0,"rvId":"016142","costEquip":2225.41121088,"costMat":0.0,"costMano":0.0},{"conMat":"0 ","cantRv":0.17,"uoId":4832,"salariomn":4.90457616,"rvId":"042726","costEquip":1.4737526100000002,"costMat":0.0,"costMano":5.35049823},{"conMat":"1 ","cantRv":0.0151,"uoId":4832,"salariomn":1.2756178000000002,"rvId":"301303","costEquip":0.0,"costMat":257.56047954,"costMano":1.3915103},{"conMat":"1 ","cantRv":0.0151,"uoId":4832,"salariomn":3.7184604056,"rvId":"305351","costEquip":0.0,"costMat":0.9314042400000001,"costMano":4.0563662728},{"conMat":"1 ","cantRv":1.73,"uoId":4832,"salariomn":22.55375742,"rvId":"311611","costEquip":0.0,"costMat":62.925463,"costMano":24.60327458},{"conMat":"0 ","cantRv":0.56,"uoId":4830,"salariomn":16.15625088,"rvId":"042726","costEquip":4.854714480000001,"costMat":0.0,"costMano":17.62517064},{"conMat":"0 ","cantRv":3.0,"uoId":4830,"salariomn":125.44505999999998,"rvId":"052812","costEquip":394.2111,"costMat":0.0,"costMano":136.82376},{"conMat":"1 ","cantRv":0.0535,"uoId":4830,"salariomn":4.519573,"rvId":"301303","costEquip":0.0,"costMat":912.5487189,"costMano":4.930185499999999},{"conMat":"1 ","cantRv":0.0535,"uoId":4830,"salariomn":13.174677595999999,"rvId":"305351","costEquip":0.0,"costMat":3.3000084,"costMano":14.371893748},{"conMat":"1 ","cantRv":4.65,"uoId":4830,"salariomn":60.621371100000005,"rvId":"311611","costEquip":0.0,"costMat":169.134915,"costMano":66.13018890000001},{"conMat":"1 ","cantRv":103.2,"uoId":4851,"salariomn":397.10844000000003,"rvId":"131811","costEquip":0.0,"costMat":55.1166432,"costMano":433.23752160000004},{"conMat":"1 ","cantRv":15.4,"uoId":4851,"salariomn":32.854206,"rvId":"131821","costEquip":0.0,"costMat":24.6743112,"costMano":35.8432228},{"conMat":"1 ","cantRv":66.6,"uoId":4851,"salariomn":166.88028599999998,"rvId":"131831","costEquip":0.0,"costMat":106.70838479999999,"costMano":182.06275499999998},{"conMat":"0 ","cantRv":29.95,"uoId":4845,"salariomn":509.1754575,"rvId":"031121","costEquip":0.0,"costMat":0.0,"costMano":555.5004403},{"conMat":"0 ","cantRv":5.1,"uoId":4845,"salariomn":74.31057,"rvId":"031131","costEquip":0.0,"costMat":0.0,"costMano":81.07137479999999},{"conMat":"0 ","cantRv":4.2,"uoId":4845,"salariomn":107.10000000000001,"rvId":"033211","costEquip":0.0,"costMat":0.0,"costMano":116.84400000000001},{"conMat":"1 ","cantRv":152.75,"uoId":4847,"salariomn":701.75183,"rvId":"141111","costEquip":0.0,"costMat":179.91811499999997,"costMano":765.57765375},{"conMat":"1 ","cantRv":3.1,"uoId":4847,"salariomn":18.2844386,"rvId":"141113","costEquip":0.0,"costMat":10.8996,"costMano":19.9474212},{"conMat":"0 ","cantRv":152.75,"uoId":4847,"salariomn":1246.44,"rvId":"144511","costEquip":0.0,"costMat":0.0,"costMano":1359.8416},{"conMat":"1 ","cantRv":169.9,"uoId":4847,"salariomn":433.245,"rvId":"146511","costEquip":0.0,"costMat":1879.4596248000003,"costMano":472.6618},{"conMat":"1 ","cantRv":152.75,"uoId":4847,"salariomn":353.18748074999996,"rvId":"148112","costEquip":622.0056375000001,"costMat":555.5212,"costMano":385.26941049999994},{"conMat":"1 ","cantRv":152.75,"uoId":4847,"salariomn":579.5020335,"rvId":"148113","costEquip":903.348225,"costMat":39.760825,"costMano":632.15327825},{"conMat":"0 ","cantRv":34.48,"uoId":4827,"salariomn":879.2399999999999,"rvId":"031161","costEquip":0.0,"costMat":0.0,"costMano":959.2335999999999},{"conMat":"1 ","cantRv":74.94,"uoId":4827,"salariomn":231.609564,"rvId":"114811","costEquip":0.0,"costMat":455.93495999999993,"costMano":252.68149295999999},{"conMat":"1 ","cantRv":0.0339,"uoId":4827,"salariomn":2.8638042,"rvId":"301303","costEquip":0.0,"costMat":578.23180506,"costMano":3.1239866999999997},{"conMat":"1 ","cantRv":0.3374,"uoId":4827,"salariomn":73.028543,"rvId":"301402","costEquip":0.0,"costMat":5755.02687396,"costMano":79.65980259999999},{"conMat":"1 ","cantRv":0.34079,"uoId":4827,"salariomn":133.92660407824,"rvId":"305331","costEquip":0.0,"costMat":25.093867176,"costMano":146.09685293712},{"conMat":"0 ","cantRv":29.95,"uoId":4852,"salariomn":509.1754575,"rvId":"031121","costEquip":0.0,"costMat":0.0,"costMano":555.5004403},{"conMat":"0 ","cantRv":5.1,"uoId":4852,"salariomn":74.31057,"rvId":"031131","costEquip":0.0,"costMat":0.0,"costMano":81.07137479999999},{"conMat":"0 ","cantRv":4.2,"uoId":4852,"salariomn":107.10000000000001,"rvId":"033211","costEquip":0.0,"costMat":0.0,"costMano":116.84400000000001},{"conMat":"0 ","cantRv":8.0,"uoId":4848,"salariomn":94.781632,"rvId":"132711","costEquip":0.0,"costMat":0.0,"costMano":103.385216},{"conMat":"1 ","cantRv":69.6,"uoId":4846,"salariomn":444.9926112,"rvId":"131101","costEquip":0.0,"costMat":755.2400399999998,"costMano":485.4776088},{"conMat":"1 ","cantRv":69.6,"uoId":4846,"salariomn":137.3208,"rvId":"131142","costEquip":0.0,"costMat":464.64612,"costMano":149.81400000000002},{"conMat":"1 ","cantRv":69.6,"uoId":4846,"salariomn":400.4903711999999,"rvId":"131201","costEquip":0.0,"costMat":387.68988719999993,"costMano":436.9265976},{"conMat":"0 ","cantRv":2.8,"uoId":4846,"salariomn":81.60306,"rvId":"132331","costEquip":0.0,"costMat":0.0,"costMano":89.02733839999999},{"conMat":"0 ","cantRv":19.3,"uoId":4846,"salariomn":393.71999999999997,"rvId":"132332","costEquip":0.0,"costMat":0.0,"costMano":429.54080000000005},{"conMat":"0 ","cantRv":2.8,"uoId":4849,"salariomn":29.3972336,"rvId":"112978","costEquip":0.0,"costMat":0.0,"costMano":32.071788},{"conMat":"1 ","cantRv":152.75,"uoId":4853,"salariomn":701.75183,"rvId":"141111","costEquip":0.0,"costMat":179.91811499999997,"costMano":765.57765375},{"conMat":"1 ","cantRv":3.1,"uoId":4853,"salariomn":18.2844386,"rvId":"141113","costEquip":0.0,"costMat":10.8996,"costMano":19.9474212},{"conMat":"0 ","cantRv":152.75,"uoId":4853,"salariomn":1246.44,"rvId":"144511","costEquip":0.0,"costMat":0.0,"costMano":1359.8416},{"conMat":"1 ","cantRv":169.9,"uoId":4853,"salariomn":433.245,"rvId":"146511","costEquip":0.0,"costMat":1879.4596248000003,"costMano":472.6618},{"conMat":"1 ","cantRv":152.75,"uoId":4853,"salariomn":353.18748074999996,"rvId":"148112","costEquip":622.0056375000001,"costMat":555.5212,"costMano":385.26941049999994},{"conMat":"1 ","cantRv":152.75,"uoId":4853,"salariomn":579.5020335,"rvId":"148113","costEquip":903.348225,"costMat":39.760825,"costMano":632.15327825},{"conMat":"0 ","cantRv":8.0,"uoId":4854,"salariomn":94.781632,"rvId":"132711","costEquip":0.0,"costMat":0.0,"costMano":103.385216},{"conMat":"0 ","cantRv":14.2,"uoId":4857,"salariomn":241.41206999999997,"rvId":"031121","costEquip":0.0,"costMat":0.0,"costMano":263.3758348},{"conMat":"1 ","cantRv":28.4,"uoId":4858,"salariomn":181.57744480000002,"rvId":"131101","costEquip":0.0,"costMat":308.17265999999995,"costMano":198.0971852},{"conMat":"1 ","cantRv":28.4,"uoId":4858,"salariomn":56.0332,"rvId":"131142","costEquip":0.0,"costMat":189.59698,"costMano":61.13100000000001},{"conMat":"1 ","cantRv":28.4,"uoId":4858,"salariomn":163.4184848,"rvId":"131201","costEquip":0.0,"costMat":158.1952988,"costMano":178.2861404},{"conMat":"0 ","cantRv":195.8,"uoId":4859,"salariomn":23643.771826400003,"rvId":"112972","costEquip":0.0,"costMat":0.0,"costMano":25794.844332400004},{"conMat":"1 ","cantRv":195.8,"uoId":4859,"salariomn":605.13948,"rvId":"114811","costEquip":0.0,"costMat":1191.2472,"costMano":660.1953072},{"conMat":"1 ","cantRv":195.8,"uoId":4859,"salariomn":1300.2980100000002,"rvId":"128111","costEquip":0.0,"costMat":3395.837720000001,"costMano":1418.3372147999999},{"conMat":"0 ","cantRv":25.3,"uoId":4860,"salariomn":1956.88416,"rvId":"112973","costEquip":0.0,"costMat":0.0,"costMano":2134.91773},{"conMat":"0 ","cantRv":6.6,"uoId":4860,"salariomn":69.2934792,"rvId":"112978","costEquip":0.0,"costMat":0.0,"costMano":75.597786},{"conMat":"0 ","cantRv":6.6,"uoId":4860,"salariomn":49.78779959999999,"rvId":"123112","costEquip":83.52828000000001,"costMat":0.0,"costMano":54.3175908},{"conMat":"1 ","cantRv":6.6,"uoId":4860,"salariomn":43.83027,"rvId":"128111","costEquip":0.0,"costMat":114.46644,"costMano":47.809119599999995},{"conMat":"1 ","cantRv":25.3,"uoId":4860,"salariomn":145.9216968,"rvId":"128191","costEquip":0.0,"costMat":378.3394384,"costMano":159.1973911},{"conMat":"0 ","cantRv":1.0,"uoId":4861,"salariomn":14.350206,"rvId":"125911","costEquip":0.0,"costMat":0.0,"costMano":15.655762},{"conMat":"0 ","cantRv":0.04,"uoId":4862,"salariomn":25.7468,"rvId":"083202","costEquip":44.220200000000006,"costMat":0.0,"costMano":28.088368000000003},{"conMat":"0 ","cantRv":1.0,"uoId":4863,"salariomn":48.971199999999996,"rvId":"097211","costEquip":0.0,"costMat":0.0,"costMano":53.4266},{"conMat":"0 ","cantRv":0.25,"uoId":4880,"salariomn":6.537855749999999,"rvId":"042724","costEquip":2.00081925,"costMat":0.0,"costMano":7.132485999999999},{"conMat":"1 ","cantRv":0.0255,"uoId":4880,"salariomn":3.445866,"rvId":"301301","costEquip":0.0,"costMat":434.9531277,"costMano":3.7588274999999998},{"conMat":"1 ","cantRv":0.0255,"uoId":4880,"salariomn":6.279519227999999,"rvId":"305351","costEquip":0.0,"costMat":1.5729012,"costMano":6.850154964},{"conMat":"1 ","cantRv":5.3,"uoId":4880,"salariomn":69.0953262,"rvId":"311611","costEquip":0.0,"costMat":192.77743,"costMano":75.3741938},{"conMat":"0 ","cantRv":78.12,"uoId":4864,"salariomn":1492.092,"rvId":"091111","costEquip":0.0,"costMat":0.0,"costMano":1627.6302},{"conMat":"0 ","cantRv":57.96,"uoId":4864,"salariomn":984.0777433200001,"rvId":"092111","costEquip":0.0,"costMat":0.0,"costMano":1073.4691035600001},{"conMat":"0 ","cantRv":30.8,"uoId":4865,"salariomn":285.57144,"rvId":"094211","costEquip":0.0,"costMat":0.0,"costMano":311.5528416},{"conMat":"0 ","cantRv":211.0,"uoId":4886,"salariomn":88.40478,"rvId":"283000","costEquip":0.0,"costMat":0.0,"costMano":96.4481},{"conMat":"0 ","cantRv":364.0,"uoId":4886,"salariomn":153.18576,"rvId":"283500","costEquip":0.0,"costMat":0.0,"costMano":167.12332},{"conMat":"1 ","cantRv":428.4,"uoId":4866,"salariomn":1208.6920440000001,"rvId":"232121","costEquip":0.0,"costMat":2143.3010507999998,"costMano":1318.4545499999997},{"conMat":"1 ","cantRv":514.7,"uoId":4866,"salariomn":2109.0553080000004,"rvId":"232122","costEquip":0.0,"costMat":2308.7892753000006,"costMano":2300.5808397},{"conMat":"1 ","cantRv":531.45,"uoId":4866,"salariomn":1499.4383445000003,"rvId":"232124","costEquip":0.0,"costMat":2809.745325900001,"costMano":1635.6038062499997},{"conMat":"1 ","cantRv":74.0,"uoId":4866,"salariomn":303.22536,"rvId":"232125","costEquip":0.0,"costMat":426.7155240000001,"costMano":330.761574},{"conMat":"1 ","cantRv":9.0,"uoId":4866,"salariomn":93.984498,"rvId":"233154","costEquip":0.0,"costMat":13.463721000000001,"costMano":102.51572399999999},{"conMat":"0 ","cantRv":2.0,"uoId":4887,"salariomn":229.5,"rvId":"252313","costEquip":0.0,"costMat":0.0,"costMano":250.38},{"conMat":"0 ","cantRv":2.0,"uoId":4887,"salariomn":102.0,"rvId":"262111","costEquip":0.0,"costMat":0.0,"costMano":111.28},{"conMat":"1 ","cantRv":31.0,"uoId":4867,"salariomn":198.20073200000002,"rvId":"131101","costEquip":0.0,"costMat":336.38564999999994,"costMano":216.232843},{"conMat":"1 ","cantRv":31.0,"uoId":4867,"salariomn":81.54816600000001,"rvId":"131141","costEquip":0.0,"costMat":206.95445,"costMano":88.96727200000001},{"conMat":"1 ","cantRv":31.0,"uoId":4867,"salariomn":178.37933199999998,"rvId":"131201","costEquip":0.0,"costMat":172.677967,"costMano":194.608111},{"conMat":"1 ","cantRv":42.05,"uoId":4867,"salariomn":536.1374999999999,"rvId":"134231","costEquip":0.0,"costMat":7350.664625999999,"costMano":584.9155},{"conMat":"0 ","cantRv":0.3,"uoId":4870,"salariomn":12.748499999999998,"rvId":"042125","costEquip":3.9015,"costMat":0.0,"costMano":13.908},{"conMat":"1 ","cantRv":0.0853,"uoId":4870,"salariomn":54.279802000000004,"rvId":"301102","costEquip":0.0,"costMat":1454.9608546200002,"costMano":59.207497700000005},{"conMat":"1 ","cantRv":0.039,"uoId":4870,"salariomn":3.2946420000000005,"rvId":"301303","costEquip":0.0,"costMat":665.2224306,"costMano":3.5939669999999997},{"conMat":"1 ","cantRv":0.0118,"uoId":4870,"salariomn":2.554051,"rvId":"301402","costEquip":0.0,"costMat":201.27242772000002,"costMano":2.7859681999999997},{"conMat":"1 ","cantRv":0.0853,"uoId":4870,"salariomn":109.65772685679998,"rvId":"305117","costEquip":0.0,"costMat":2.37987,"costMano":119.6122259384},{"conMat":"1 ","cantRv":0.0508,"uoId":4870,"salariomn":8.4647532,"rvId":"305323","costEquip":0.0,"costMat":2.3233075199999997,"costMano":9.2339668},{"conMat":"1 ","cantRv":6.54,"uoId":4870,"salariomn":92.48267627999999,"rvId":"311311","costEquip":0.0,"costMat":237.880074,"costMano":100.88681172},{"conMat":"0 ","cantRv":2.0,"uoId":4888,"salariomn":23.08,"rvId":"038111","costEquip":0.0,"costMat":0.0,"costMano":25.18},{"conMat":"0 ","cantRv":2.0,"uoId":4888,"salariomn":7.173827999999999,"rvId":"131911","costEquip":0.0,"costMat":0.0,"costMano":7.82649},{"conMat":"0 ","cantRv":6.0,"uoId":4888,"salariomn":18.085463999999998,"rvId":"172244","costEquip":0.0,"costMat":0.0,"costMano":19.728935999999997},{"conMat":"0 ","cantRv":21.1,"uoId":4888,"salariomn":69.95010810000001,"rvId":"172257","costEquip":0.0,"costMat":0.0,"costMano":76.3066519},{"conMat":"0 ","cantRv":2.0,"uoId":4888,"salariomn":54.879999999999995,"rvId":"172273","costEquip":0.0,"costMat":0.0,"costMano":59.879999999999995},{"conMat":"0 ","cantRv":1.0,"uoId":4888,"salariomn":13.6017,"rvId":"179143","costEquip":0.0,"costMat":0.0,"costMano":14.839188},{"conMat":"0 ","cantRv":0.11,"uoId":4871,"salariomn":3.7395599999999996,"rvId":"042424","costEquip":1.1444400000000001,"costMat":0.0,"costMano":4.07968},{"conMat":"1 ","cantRv":0.006,"uoId":4871,"salariomn":0.5068680000000001,"rvId":"301303","costEquip":0.0,"costMat":102.34191240000001,"costMano":0.5529179999999999},{"conMat":"1 ","cantRv":0.0031,"uoId":4871,"salariomn":1.0966064,"rvId":"301401","costEquip":0.0,"costMat":52.87665474,"costMano":1.1961690999999999},{"conMat":"1 ","cantRv":0.0091,"uoId":4871,"salariomn":1.5163239000000002,"rvId":"305321","costEquip":0.0,"costMat":0.41618304,"costMano":1.6541161},{"conMat":"1 ","cantRv":1.86,"uoId":4871,"salariomn":52.003468440000006,"rvId":"311511","costEquip":0.0,"costMat":77.281512,"costMano":56.72915556000001},{"conMat":"0 ","cantRv":8.0,"uoId":4889,"salariomn":92.32,"rvId":"038111","costEquip":0.0,"costMat":0.0,"costMano":100.72},{"conMat":"0 ","cantRv":8.0,"uoId":4889,"salariomn":28.695311999999998,"rvId":"131911","costEquip":0.0,"costMat":0.0,"costMano":31.30596},{"conMat":"0 ","cantRv":6.0,"uoId":4889,"salariomn":5.250744,"rvId":"178411","costEquip":0.0,"costMat":0.0,"costMano":5.730264000000001},{"conMat":"0 ","cantRv":8.0,"uoId":4889,"salariomn":7.000992,"rvId":"178413","costEquip":0.0,"costMat":0.0,"costMano":7.640352000000001},{"conMat":"0 ","cantRv":0.85,"uoId":4872,"salariomn":28.896599999999996,"rvId":"042424","costEquip":8.8434,"costMat":0.0,"costMano":31.5248},{"conMat":"1 ","cantRv":0.0156,"uoId":4872,"salariomn":1.3178568000000002,"rvId":"301303","costEquip":0.0,"costMat":266.08897224000003,"costMano":1.4375867999999998},{"conMat":"1 ","cantRv":0.0166,"uoId":4872,"salariomn":5.872150400000001,"rvId":"301401","costEquip":0.0,"costMat":283.14595764,"costMano":6.4052926},{"conMat":"1 ","cantRv":0.055,"uoId":4872,"salariomn":11.904475,"rvId":"301402","costEquip":0.0,"costMat":938.1341970000001,"costMano":12.985445},{"conMat":"1 ","cantRv":0.0872,"uoId":4872,"salariomn":14.530048800000001,"rvId":"305321","costEquip":0.0,"costMat":3.98803968,"costMano":15.8504312},{"conMat":"1 ","cantRv":15.0,"uoId":4872,"salariomn":344.77281,"rvId":"311521","costEquip":0.0,"costMat":311.61899999999997,"costMano":376.10319},{"conMat":"0 ","cantRv":0.25,"uoId":4874,"salariomn":8.498999999999999,"rvId":"042424","costEquip":2.6010000000000004,"costMat":0.0,"costMano":9.272},{"conMat":"1 ","cantRv":0.0086,"uoId":4874,"salariomn":5.472524,"rvId":"301102","costEquip":0.0,"costMat":146.69007444000002,"costMano":5.969337400000001},{"conMat":"1 ","cantRv":0.0118,"uoId":4874,"salariomn":0.9968404000000001,"rvId":"301303","costEquip":0.0,"costMat":201.27242772000002,"costMano":1.0874054},{"conMat":"1 ","cantRv":0.0086,"uoId":4874,"salariomn":11.055761441599998,"rvId":"305112","costEquip":0.0,"costMat":0.23994,"costMano":12.059380340799999},{"conMat":"1 ","cantRv":0.0118,"uoId":4874,"salariomn":1.9662222000000003,"rvId":"305321","costEquip":0.0,"costMat":0.53966592,"costMano":2.1448978},{"conMat":"1 ","cantRv":2.6,"uoId":4874,"salariomn":72.69302040000001,"rvId":"311511","costEquip":0.0,"costMat":108.02792,"costMano":79.2988196},{"conMat":"0 ","cantRv":0.32,"uoId":4875,"salariomn":8.368455359999999,"rvId":"042724","costEquip":2.56104864,"costMat":0.0,"costMano":9.129582079999999},{"conMat":"0 ","cantRv":0.2,"uoId":4875,"salariomn":0.233778,"rvId":"087311","costEquip":0.0,"costMat":0.0,"costMano":0.255022},{"conMat":"1 ","cantRv":0.0377,"uoId":4875,"salariomn":3.1848206,"rvId":"301303","costEquip":0.0,"costMat":643.04834958,"costMano":3.4741680999999995},{"conMat":"1 ","cantRv":2.0E-4,"uoId":4875,"salariomn":0.07074880000000001,"rvId":"301401","costEquip":0.0,"costMat":3.4113970800000004,"costMano":0.0771722},{"conMat":"1 ","cantRv":0.0379,"uoId":4875,"salariomn":9.3330893624,"rvId":"305351","costEquip":0.0,"costMat":2.33776296,"costMano":10.181210711200002},{"conMat":"1 ","cantRv":3.85,"uoId":4875,"salariomn":50.1918879,"rvId":"311611","costEquip":0.0,"costMat":140.036435,"costMano":54.7529521},{"conMat":"0 ","cantRv":8.0,"uoId":4877,"salariomn":194.09855999999996,"rvId":"052911","costEquip":578.232,"costMat":0.0,"costMano":211.70335999999998},{"conMat":"0 ","cantRv":1.11,"uoId":4878,"salariomn":47.169450000000005,"rvId":"042125","costEquip":14.435550000000003,"costMat":0.0,"costMano":51.4596},{"conMat":"1 ","cantRv":75.0,"uoId":4878,"salariomn":231.79500000000002,"rvId":"114811","costEquip":0.0,"costMat":456.29999999999995,"costMano":252.88379999999998},{"conMat":"1 ","cantRv":0.044,"uoId":4878,"salariomn":3.717032,"rvId":"301303","costEquip":0.0,"costMat":750.5073576,"costMano":4.054732},{"conMat":"1 ","cantRv":0.031,"uoId":4878,"salariomn":6.709795,"rvId":"301402","costEquip":0.0,"costMat":528.7665474,"costMano":7.319069},{"conMat":"1 ","cantRv":0.075,"uoId":4878,"salariomn":12.497175,"rvId":"305323","costEquip":0.0,"costMat":3.43008,"costMano":13.632824999999999},{"conMat":"1 ","cantRv":33.6,"uoId":4878,"salariomn":259.78848,"rvId":"306411","costEquip":1327.0824000000002,"costMat":102.4128,"costMano":283.42608},{"conMat":"1 ","cantRv":14.6,"uoId":4878,"salariomn":206.45979719999997,"rvId":"311311","costEquip":0.0,"costMat":531.04726,"costMano":225.22132279999997},{"conMat":"0 ","cantRv":458.28,"uoId":4868,"salariomn":2125.6195013999995,"rvId":"316330","costEquip":0.0,"costMat":0.0,"costMano":2318.7799385999997},{"conMat":"0 ","cantRv":424.9,"uoId":4868,"salariomn":7511.72212,"rvId":"316333","costEquip":0.0,"costMat":0.0,"costMano":8194.02654},{"conMat":"0 ","cantRv":0.62,"uoId":4869,"salariomn":26.346899999999998,"rvId":"042125","costEquip":8.0631,"costMat":0.0,"costMano":28.743199999999998},{"conMat":"1 ","cantRv":0.0231,"uoId":4869,"salariomn":14.699454,"rvId":"301102","costEquip":0.0,"costMat":394.01636274000003,"costMano":16.0339179},{"conMat":"1 ","cantRv":0.0745,"uoId":4869,"salariomn":5.0826135,"rvId":"301305","costEquip":0.0,"costMat":1054.8453510000002,"costMano":5.5443644999999995},{"conMat":"1 ","cantRv":0.0231,"uoId":4869,"salariomn":29.696289453599995,"rvId":"305117","costEquip":0.0,"costMat":0.6444899999999999,"costMano":32.392056496799995},{"conMat":"1 ","cantRv":0.0745,"uoId":4869,"salariomn":12.4138605,"rvId":"305323","costEquip":0.0,"costMat":3.4072128,"costMano":13.541939499999998},{"conMat":"1 ","cantRv":9.88,"uoId":4869,"salariomn":139.71389016,"rvId":"311311","costEquip":0.0,"costMat":359.36622800000004,"costMano":152.41004584},{"conMat":"0 ","cantRv":0.45,"uoId":4873,"salariomn":11.76814035,"rvId":"042724","costEquip":3.6014746500000006,"costMat":0.0,"costMano":12.838474799999998},{"conMat":"1 ","cantRv":0.0319,"uoId":4873,"salariomn":2.6948482,"rvId":"301303","costEquip":0.0,"costMat":544.11783426,"costMano":2.9396806999999994},{"conMat":"1 ","cantRv":0.0319,"uoId":4873,"salariomn":7.855555426399999,"rvId":"305351","costEquip":0.0,"costMat":1.96766856,"costMano":8.569409543199999},{"conMat":"1 ","cantRv":7.35,"uoId":4873,"salariomn":95.8208769,"rvId":"311611","costEquip":0.0,"costMat":267.342285,"costMano":104.52836309999999},{"conMat":"0 ","cantRv":0.2,"uoId":4876,"salariomn":6.799199999999999,"rvId":"042424","costEquip":2.0808000000000004,"costMat":0.0,"costMano":7.4176},{"conMat":"1 ","cantRv":37.0,"uoId":4876,"salariomn":114.35220000000001,"rvId":"114811","costEquip":0.0,"costMat":225.10799999999998,"costMano":124.756008},{"conMat":"1 ","cantRv":0.0055,"uoId":4876,"salariomn":0.464629,"rvId":"301303","costEquip":0.0,"costMat":93.8134197,"costMano":0.5068415},{"conMat":"1 ","cantRv":0.0055,"uoId":4876,"salariomn":1.3544061079999998,"rvId":"305351","costEquip":0.0,"costMat":0.3392532,"costMano":1.477484404},{"conMat":"1 ","cantRv":3.75,"uoId":4876,"salariomn":28.99425,"rvId":"306411","costEquip":148.11187500000003,"costMat":11.43,"costMano":31.632375},{"conMat":"1 ","cantRv":1.3,"uoId":4876,"salariomn":16.9479102,"rvId":"311611","costEquip":0.0,"costMat":47.285030000000006,"costMano":18.4880098},{"conMat":"0 ","cantRv":10.0,"uoId":4879,"salariomn":335.72400000000005,"rvId":"052601","costEquip":1124.708,"costMat":0.0,"costMano":366.19599999999997},{"conMat":"0 ","cantRv":18.0,"uoId":4881,"salariomn":143.25119999999998,"rvId":"261201","costEquip":0.0,"costMat":0.0,"costMano":156.2688},{"conMat":"0 ","cantRv":10.0,"uoId":4882,"salariomn":39.791999999999994,"rvId":"263411","costEquip":0.0,"costMat":0.0,"costMano":43.408},{"conMat":"0 ","cantRv":6.0,"uoId":4883,"salariomn":23.8752,"rvId":"263511","costEquip":0.0,"costMat":0.0,"costMano":26.0448},{"conMat":"0 ","cantRv":1.0,"uoId":4885,"salariomn":32.331,"rvId":"277301","costEquip":0.0,"costMat":0.0,"costMano":35.269000000000005},{"conMat":"1 ","cantRv":1.16,"uoId":4885,"salariomn":62.8024,"rvId":"277501","costEquip":0.0,"costMat":320.15999999999997,"costMano":68.50959999999999},{"conMat":"1 ","cantRv":0.32,"uoId":4885,"salariomn":27.71968,"rvId":"277504","costEquip":0.0,"costMat":97.92,"costMano":30.238720000000004},{"conMat":"1 ","cantRv":30.0,"uoId":4885,"salariomn":97.452,"rvId":"278310","costEquip":0.0,"costMat":41.4,"costMano":106.30799999999999},{"conMat":"1 ","cantRv":162.0,"uoId":4885,"salariomn":210.49632000000003,"rvId":"278420","costEquip":0.0,"costMat":374.22,"costMano":229.62528},{"conMat":"1 ","cantRv":36.0,"uoId":4884,"salariomn":100.70265599999999,"rvId":"038211","costEquip":0.0,"costMat":0.0,"costMano":109.865376},{"conMat":"0 ","cantRv":18.0,"uoId":4884,"salariomn":210.40019999999998,"rvId":"273701","costEquip":0.0,"costMat":0.0,"costMano":229.51979999999998},{"conMat":"1 ","cantRv":36.0,"uoId":4884,"salariomn":329.5728,"rvId":"273711","costEquip":0.0,"costMat":310.67999999999995,"costMano":359.5536}],"suministros":[{"unidadobraId":4831,"tipo":"S","costo":57.737256,"idSuministro":"0002204344","idRenglon":122972,"id":14030,"cantidad":0.0808},{"unidadobraId":4829,"tipo":"S","costo":736.150014,"idSuministro":"0002204344","idRenglon":122962,"id":14026,"cantidad":1.0302},{"unidadobraId":4855,"tipo":"S","costo":755.24,"idSuministro":"0002204022","idRenglon":126328,"id":14083,"cantidad":1.044},{"unidadobraId":4855,"tipo":"1","costo":9.48,"idSuministro":"4402010102","idRenglon":126420,"id":14084,"cantidad":0.056},{"unidadobraId":4855,"tipo":"1","costo":126.64,"idSuministro":"4491010710","idRenglon":126420,"id":14085,"cantidad":0.0736},{"unidadobraId":4855,"tipo":"S","costo":58.43,"idSuministro":"0002204131","idRenglon":126420,"id":14086,"cantidad":0.056},{"unidadobraId":4855,"tipo":"1","costo":65.36,"idSuministro":"4402010102","idRenglon":126421,"id":14087,"cantidad":0.386},{"unidadobraId":4855,"tipo":"1","costo":873.43,"idSuministro":"4491010710","idRenglon":126421,"id":14088,"cantidad":0.5076},{"unidadobraId":4855,"tipo":"S","costo":402.73,"idSuministro":"0002204131","idRenglon":126421,"id":14089,"cantidad":0.386},{"unidadobraId":4856,"tipo":"1","costo":92.11,"idSuministro":"4572990001","idRenglon":125498,"id":14090,"cantidad":0.0045},{"unidadobraId":4856,"tipo":"1","costo":113.6,"idSuministro":"4579010111","idRenglon":125498,"id":14091,"cantidad":2.8},{"unidadobraId":4828,"tipo":"S","costo":144.34314,"idSuministro":"0002204344","idRenglon":122955,"id":14025,"cantidad":0.202},{"unidadobraId":4850,"tipo":"S","costo":55.14,"idSuministro":"0002204122","idRenglon":126403,"id":14071,"cantidad":0.0413},{"unidadobraId":4825,"tipo":"1","costo":848.2,"idSuministro":"4414990001","idRenglon":121960,"id":14050,"cantidad":48.2482},{"unidadobraId":4832,"tipo":"S","costo":122.691669,"idSuministro":"0002204344","idRenglon":122972,"id":14031,"cantidad":0.1717},{"unidadobraId":4830,"tipo":"S","costo":404.160792,"idSuministro":"0002204344","idRenglon":122972,"id":14028,"cantidad":0.5656},{"unidadobraId":4830,"tipo":"1","costo":3.02,"idSuministro":"3161098116","idRenglon":123441,"id":14029,"cantidad":0.6},{"unidadobraId":4851,"tipo":"S","costo":55.14,"idSuministro":"0002204122","idRenglon":126403,"id":14072,"cantidad":0.0413},{"unidadobraId":4845,"tipo":"1","costo":1404.63,"idSuministro":"4472010002","idRenglon":122562,"id":14051,"cantidad":0.3923},{"unidadobraId":4845,"tipo":"S","costo":277.36,"idSuministro":"0002204022","idRenglon":122562,"id":14052,"cantidad":0.3834},{"unidadobraId":4845,"tipo":"1","costo":158.75,"idSuministro":"4472010001","idRenglon":122566,"id":14053,"cantidad":0.0653},{"unidadobraId":4845,"tipo":"S","costo":62.44,"idSuministro":"0002204123","idRenglon":122566,"id":14054,"cantidad":0.0612},{"unidadobraId":4845,"tipo":"1","costo":74.27,"idSuministro":"4483990101","idRenglon":122648,"id":14055,"cantidad":0.084},{"unidadobraId":4845,"tipo":"S","costo":54.69,"idSuministro":"0002204022","idRenglon":122648,"id":14056,"cantidad":0.0756},{"unidadobraId":4847,"tipo":"1","costo":517.27,"idSuministro":"4402010102","idRenglon":126964,"id":14064,"cantidad":3.055},{"unidadobraId":4847,"tipo":"1","costo":16082.05,"idSuministro":"4481060012","idRenglon":126964,"id":14065,"cantidad":160.3875},{"unidadobraId":4847,"tipo":"S","costo":3646.57,"idSuministro":"0002204022","idRenglon":126964,"id":14066,"cantidad":5.0408},{"unidadobraId":4827,"tipo":"S","costo":804.73,"idSuministro":"0002204123","idRenglon":122572,"id":14024,"cantidad":0.7888},{"unidadobraId":4852,"tipo":"1","costo":1404.63,"idSuministro":"4472010002","idRenglon":122562,"id":14073,"cantidad":0.3923},{"unidadobraId":4852,"tipo":"S","costo":277.36,"idSuministro":"0002204022","idRenglon":122562,"id":14074,"cantidad":0.3834},{"unidadobraId":4852,"tipo":"1","costo":158.75,"idSuministro":"4472010001","idRenglon":122566,"id":14075,"cantidad":0.0653},{"unidadobraId":4852,"tipo":"S","costo":62.44,"idSuministro":"0002204123","idRenglon":122566,"id":14076,"cantidad":0.0612},{"unidadobraId":4852,"tipo":"1","costo":74.27,"idSuministro":"4483990101","idRenglon":122648,"id":14077,"cantidad":0.084},{"unidadobraId":4852,"tipo":"S","costo":54.69,"idSuministro":"0002204022","idRenglon":122648,"id":14078,"cantidad":0.0756},{"unidadobraId":4848,"tipo":"1","costo":16.25,"idSuministro":"4402010102","idRenglon":126441,"id":14067,"cantidad":0.096},{"unidadobraId":4846,"tipo":"S","costo":755.24,"idSuministro":"0002204022","idRenglon":126328,"id":14057,"cantidad":1.044},{"unidadobraId":4846,"tipo":"1","costo":9.48,"idSuministro":"4402010102","idRenglon":126420,"id":14058,"cantidad":0.056},{"unidadobraId":4846,"tipo":"1","costo":126.64,"idSuministro":"4491010710","idRenglon":126420,"id":14059,"cantidad":0.0736},{"unidadobraId":4846,"tipo":"S","costo":58.43,"idSuministro":"0002204131","idRenglon":126420,"id":14060,"cantidad":0.056},{"unidadobraId":4846,"tipo":"1","costo":65.36,"idSuministro":"4402010102","idRenglon":126421,"id":14061,"cantidad":0.386},{"unidadobraId":4846,"tipo":"1","costo":873.43,"idSuministro":"4491010710","idRenglon":126421,"id":14062,"cantidad":0.5076},{"unidadobraId":4846,"tipo":"S","costo":402.73,"idSuministro":"0002204131","idRenglon":126421,"id":14063,"cantidad":0.386},{"unidadobraId":4849,"tipo":"1","costo":92.11,"idSuministro":"4572990001","idRenglon":125498,"id":14069,"cantidad":0.0045},{"unidadobraId":4849,"tipo":"1","costo":113.6,"idSuministro":"4579010111","idRenglon":125498,"id":14070,"cantidad":2.8},{"unidadobraId":4853,"tipo":"1","costo":517.27,"idSuministro":"4402010102","idRenglon":126964,"id":14079,"cantidad":3.055},{"unidadobraId":4853,"tipo":"1","costo":16082.05,"idSuministro":"4481060012","idRenglon":126964,"id":14080,"cantidad":160.3875},{"unidadobraId":4853,"tipo":"S","costo":3646.57,"idSuministro":"0002204022","idRenglon":126964,"id":14081,"cantidad":5.0408},{"unidadobraId":4854,"tipo":"1","costo":16.25,"idSuministro":"4402010102","idRenglon":126441,"id":14082,"cantidad":0.096},{"unidadobraId":4857,"tipo":"1","costo":665.97,"idSuministro":"4472010002","idRenglon":122562,"id":14092,"cantidad":0.186},{"unidadobraId":4857,"tipo":"S","costo":131.52,"idSuministro":"0002204022","idRenglon":122562,"id":14093,"cantidad":0.1818},{"unidadobraId":4860,"tipo":"1","costo":216.98,"idSuministro":"4572990001","idRenglon":125498,"id":14094,"cantidad":0.0106},{"unidadobraId":4860,"tipo":"1","costo":99.87,"idSuministro":"4401010012","idRenglon":126067,"id":14096,"cantidad":1.1781},{"unidadobraId":4860,"tipo":"1","costo":267.76,"idSuministro":"4579010111","idRenglon":125498,"id":14095,"cantidad":6.6},{"unidadobraId":4860,"tipo":"1","costo":15.66,"idSuministro":"4414990001","idRenglon":126067,"id":14097,"cantidad":0.891},{"unidadobraId":4861,"tipo":"1","costo":0.02,"idSuministro":"4421030001","idRenglon":126111,"id":14099,"cantidad":9.0E-4},{"unidadobraId":4861,"tipo":"1","costo":0.15,"idSuministro":"4401010011","idRenglon":126111,"id":14098,"cantidad":1.0E-4},{"unidadobraId":4862,"tipo":"1","costo":0.93,"idSuministro":"3161098112","idRenglon":124618,"id":14100,"cantidad":0.184},{"unidadobraId":4862,"tipo":"1","costo":242.58,"idSuministro":"3199999999","idRenglon":124618,"id":14101,"cantidad":0.04},{"unidadobraId":4863,"tipo":"1","costo":162.15,"idSuministro":"3199620111","idRenglon":124949,"id":14102,"cantidad":1.0},{"unidadobraId":4863,"tipo":"S","costo":21.75,"idSuministro":"0002204132","idRenglon":124949,"id":14104,"cantidad":0.024},{"unidadobraId":4863,"tipo":"1","costo":38.69,"idSuministro":"4542010001","idRenglon":124949,"id":14103,"cantidad":0.025},{"unidadobraId":4864,"tipo":"1","costo":61.72,"idSuministro":"3032012253","idRenglon":124832,"id":14105,"cantidad":5.3903},{"unidadobraId":4864,"tipo":"1","costo":19024.56,"idSuministro":"4783029200","idRenglon":124832,"id":14107,"cantidad":78.12},{"unidadobraId":4864,"tipo":"1","costo":249.23,"idSuministro":"3037111071","idRenglon":124868,"id":14109,"cantidad":579.6},{"unidadobraId":4864,"tipo":"1","costo":596.41,"idSuministro":"4562030001","idRenglon":124868,"id":14111,"cantidad":57.96},{"unidadobraId":4864,"tipo":"1","costo":335.92,"idSuministro":"3037111071","idRenglon":124832,"id":14106,"cantidad":781.2},{"unidadobraId":4864,"tipo":"1","costo":45.79,"idSuministro":"3032012253","idRenglon":124868,"id":14108,"cantidad":3.9992},{"unidadobraId":4864,"tipo":"1","costo":270.63,"idSuministro":"3999411313","idRenglon":124868,"id":14110,"cantidad":20.8656},{"unidadobraId":4864,"tipo":"1","costo":27468.4,"idSuministro":"4783019000","idRenglon":124868,"id":14112,"cantidad":57.96},{"unidadobraId":4865,"tipo":"1","costo":2641.41,"idSuministro":"4782041111","idRenglon":124921,"id":14113,"cantidad":30.8},{"unidadobraId":4865,"tipo":"S","costo":103.65,"idSuministro":"0002204123","idRenglon":124921,"id":14114,"cantidad":0.1016},{"unidadobraId":4886,"tipo":"1","costo":71.74,"idSuministro":"6763120830","idRenglon":132680,"id":14125,"cantidad":211.0},{"unidadobraId":4886,"tipo":"1","costo":123.76,"idSuministro":"6763120830","idRenglon":132809,"id":14126,"cantidad":364.0},{"unidadobraId":4887,"tipo":"1","costo":2.33,"idSuministro":"2725993675","idRenglon":131808,"id":14127,"cantidad":1.0},{"unidadobraId":4887,"tipo":"1","costo":0.42,"idSuministro":"3034401009","idRenglon":131808,"id":14129,"cantidad":0.008},{"unidadobraId":4887,"tipo":"1","costo":0.24,"idSuministro":"3031451005","idRenglon":131933,"id":14131,"cantidad":0.024},{"unidadobraId":4887,"tipo":"1","costo":0.11,"idSuministro":"3034401005","idRenglon":131933,"id":14133,"cantidad":0.008},{"unidadobraId":4887,"tipo":"1","costo":1.47,"idSuministro":"3035015061","idRenglon":131933,"id":14135,"cantidad":0.08},{"unidadobraId":4887,"tipo":"1","costo":0.5,"idSuministro":"3031451009","idRenglon":131808,"id":14128,"cantidad":0.0602},{"unidadobraId":4887,"tipo":"1","costo":22.81,"idSuministro":"3035015298","idRenglon":131808,"id":14130,"cantidad":0.08},{"unidadobraId":4887,"tipo":"1","costo":1.69,"idSuministro":"3034163026","idRenglon":131933,"id":14132,"cantidad":0.08},{"unidadobraId":4887,"tipo":"1","costo":1.08,"idSuministro":"3035015057","idRenglon":131933,"id":14134,"cantidad":0.08},{"unidadobraId":4887,"tipo":"1","costo":56.56,"idSuministro":"3037131071","idRenglon":131933,"id":14136,"cantidad":8.0},{"unidadobraId":4888,"tipo":"1","costo":84.98,"idSuministro":"3748909041","idRenglon":127814,"id":14144,"cantidad":6.18},{"unidadobraId":4888,"tipo":"1","costo":46.43,"idSuministro":"3748909051","idRenglon":127823,"id":14146,"cantidad":2.06},{"unidadobraId":4888,"tipo":"1","costo":311.0,"idSuministro":"3748909022","idRenglon":127817,"id":14145,"cantidad":21.733},{"unidadobraId":4889,"tipo":"S","costo":17.36,"idSuministro":"0002204022","idRenglon":126407,"id":14147,"cantidad":0.024},{"unidadobraId":4889,"tipo":"1","costo":82.73,"idSuministro":"3748929221","idRenglon":128130,"id":14149,"cantidad":8.24},{"unidadobraId":4889,"tipo":"1","costo":17.37,"idSuministro":"3748929201","idRenglon":128128,"id":14148,"cantidad":6.18},{"unidadobraId":4875,"tipo":"1","costo":0.61,"idSuministro":"2723620000","idRenglon":124772,"id":14115,"cantidad":2.0E-4},{"unidadobraId":4879,"tipo":"1","costo":10.06,"idSuministro":"3161098116","idRenglon":123411,"id":14116,"cantidad":2.0},{"unidadobraId":4881,"tipo":"1","costo":0.79,"idSuministro":"6791011002","idRenglon":131906,"id":14118,"cantidad":1.44},{"unidadobraId":4881,"tipo":"1","costo":721.44,"idSuministro":"5282991120","idRenglon":131906,"id":14117,"cantidad":18.0},{"unidadobraId":4882,"tipo":"1","costo":19.6,"idSuministro":"6798082101","idRenglon":131962,"id":14120,"cantidad":10.0},{"unidadobraId":4882,"tipo":"1","costo":0.44,"idSuministro":"6791011002","idRenglon":131962,"id":14119,"cantidad":0.8},{"unidadobraId":4883,"tipo":"1","costo":15.06,"idSuministro":"6798062202","idRenglon":131971,"id":14122,"cantidad":6.0},{"unidadobraId":4883,"tipo":"1","costo":0.26,"idSuministro":"6791011002","idRenglon":131971,"id":14121,"cantidad":0.48},{"unidadobraId":4885,"tipo":"1","costo":41.4,"idSuministro":"3745010401","idRenglon":132488,"id":14124,"cantidad":15.0},{"unidadobraId":4885,"tipo":"1","costo":276.0,"idSuministro":"3745010401","idRenglon":132364,"id":14123,"cantidad":100.0},{"unidadobraId":4884,"tipo":"1","costo":0.48,"idSuministro":"2615100160","idRenglon":132234,"id":14137,"cantidad":0.18},{"unidadobraId":4884,"tipo":"1","costo":14.76,"idSuministro":"2708576310","idRenglon":132234,"id":14139,"cantidad":18.0},{"unidadobraId":4884,"tipo":"1","costo":40.68,"idSuministro":"2708994035","idRenglon":132234,"id":14141,"cantidad":18.0},{"unidadobraId":4884,"tipo":"1","costo":29.88,"idSuministro":"3745050261","idRenglon":132234,"id":14143,"cantidad":18.0},{"unidadobraId":4884,"tipo":"1","costo":7.74,"idSuministro":"2708561003","idRenglon":132234,"id":14138,"cantidad":18.0},{"unidadobraId":4884,"tipo":"1","costo":64.08,"idSuministro":"2708993001","idRenglon":132234,"id":14140,"cantidad":18.0},{"unidadobraId":4884,"tipo":"1","costo":62.28,"idSuministro":"3745010411","idRenglon":132234,"id":14142,"cantidad":18.0}],"obraEmpresas":["12889"],"subespecialidades":[{"code":"02","descrip":"SUPER-ESTRUCTURA","id":177,"idE":18},{"code":"01","descrip":"ILUMINACI?N","id":175,"idE":16},{"code":"01","descrip":"RED SANITARIA","id":178,"idE":19},{"code":"03","descrip":"CISTERNA","id":191,"idE":18},{"code":"01","descrip":"ALBA?ILER?A","id":182,"idE":15},{"code":"02","descrip":"RED HIDRA?LICA","id":179,"idE":19}],"cuadrillas":[],"tipoobra":1,"especialidades":[{"code":"13","descrip":"ARQUITECTURA","id":15},{"code":"15","descrip":"ESTRUCTURA","id":18},{"code":"14","descrip":"ELECTRICIDAD","id":16},{"code":"16","descrip":"HIDROSANITARIA","id":19}],"entidad":"12928","unidades":[{"descripcion":"LOSA DE TAPA","objetosId":"01","codigo":"07","idzona":"001","empresaconstructoraId":"12889","costoMaterial":134.767256,"salario":3.8,"costoequipo":0.69,"especialidadesId":"15","costomano":4.14,"subespecialidadesId":"03","nivelId":"01","obraId":214,"id":4831},{"descripcion":"CERRAMENTO","objetosId":"01","codigo":"05","idzona":"001","empresaconstructoraId":"12889","costoMaterial":2194.400014,"salario":331.7,"costoequipo":10.61,"especialidadesId":"15","costomano":361.84,"subespecialidadesId":"03","nivelId":"01","obraId":214,"id":4829},{"descripcion":"ENCHAPES Y REVESTIMIENTOS","objetosId":"02","codigo":"02","idzona":"001","empresaconstructoraId":"12889","costoMaterial":3898.89,"salario":1458.13,"costoequipo":0.0,"especialidadesId":"13","costomano":1590.79,"subespecialidadesId":"01","nivelId":"02","obraId":214,"id":4855},{"descripcion":"IMPERMEABILIZACIÓN ZONAS HÚMEDAS","objetosId":"02","codigo":"05","idzona":"001","empresaconstructoraId":"12889","costoMaterial":205.70999999999998,"salario":29.4,"costoequipo":0.0,"especialidadesId":"13","costomano":32.07,"subespecialidadesId":"01","nivelId":"02","obraId":214,"id":4856},{"descripcion":"PILASTRAS","objetosId":"01","codigo":"04","idzona":"001","empresaconstructoraId":"12889","costoMaterial":2896.20314,"salario":452.78,"costoequipo":22.11,"especialidadesId":"15","costomano":493.92,"subespecialidadesId":"03","nivelId":"01","obraId":214,"id":4828},{"descripcion":"LOSA DE FONDO","objetosId":"01","codigo":"02","idzona":"001","empresaconstructoraId":"12889","costoMaterial":13501.2,"salario":629.68,"costoequipo":40.0,"especialidadesId":"15","costomano":686.92,"subespecialidadesId":"03","nivelId":"01","obraId":214,"id":4826},{"descripcion":"JUNTA ENTRE ELEMENTOS PREFABRICADOS","objetosId":"02","codigo":"06","idzona":"001","empresaconstructoraId":"12889","costoMaterial":241.64,"salario":596.84,"costoequipo":0.0,"especialidadesId":"13","costomano":651.14,"subespecialidadesId":"01","nivelId":"01","obraId":214,"id":4850},{"descripcion":"MOVIMIENTO DE TIERRA","objetosId":"01","codigo":"01","idzona":"001","empresaconstructoraId":"12889","costoMaterial":848.2,"salario":3051.27,"costoequipo":16211.94,"especialidadesId":"15","costomano":3328.9,"subespecialidadesId":"03","nivelId":"01","obraId":214,"id":4825},{"descripcion":"LOSA TAPA DE CASETA DE BOMBA","objetosId":"01","codigo":"08","idzona":"001","empresaconstructoraId":"12889","costoMaterial":444.111669,"salario":32.45,"costoequipo":1.47,"especialidadesId":"15","costomano":35.4,"subespecialidadesId":"03","nivelId":"01","obraId":214,"id":4832},{"descripcion":"LOSA DE CIERRE","objetosId":"01","codigo":"06","idzona":"001","empresaconstructoraId":"12889","costoMaterial":1492.1607920000001,"salario":219.92,"costoequipo":399.07,"especialidadesId":"15","costomano":239.88,"subespecialidadesId":"03","nivelId":"01","obraId":214,"id":4830},{"descripcion":"JUNTA ENTRE ELEMENTOS PREFABRICADOS","objetosId":"02","codigo":"06","idzona":"001","empresaconstructoraId":"12889","costoMaterial":241.64,"salario":596.84,"costoequipo":0.0,"especialidadesId":"13","costomano":651.14,"subespecialidadesId":"01","nivelId":"02","obraId":214,"id":4851},{"descripcion":"MUROS","objetosId":"02","codigo":"01","idzona":"001","empresaconstructoraId":"12889","costoMaterial":2032.1400000000003,"salario":690.59,"costoequipo":0.0,"especialidadesId":"13","costomano":753.42,"subespecialidadesId":"01","nivelId":"01","obraId":214,"id":4845},{"descripcion":"PISOS","objetosId":"02","codigo":"03","idzona":"001","empresaconstructoraId":"12889","costoMaterial":22911.45,"salario":3332.41,"costoequipo":1525.35,"especialidadesId":"13","costomano":3635.45,"subespecialidadesId":"01","nivelId":"01","obraId":214,"id":4847},{"descripcion":"MUROS DE BLOQUES MACIZADOS Y REFORZADOS","objetosId":"01","codigo":"03","idzona":"001","empresaconstructoraId":"12889","costoMaterial":7619.02,"salario":1320.67,"costoequipo":0.0,"especialidadesId":"15","costomano":1440.8,"subespecialidadesId":"03","nivelId":"01","obraId":214,"id":4827},{"descripcion":"MUROS","objetosId":"02","codigo":"01","idzona":"001","empresaconstructoraId":"12889","costoMaterial":2032.1400000000003,"salario":690.59,"costoequipo":0.0,"especialidadesId":"13","costomano":753.42,"subespecialidadesId":"01","nivelId":"02","obraId":214,"id":4852},{"descripcion":"ACCESORIOS SANITARIOS","objetosId":"02","codigo":"04","idzona":"001","empresaconstructoraId":"12889","costoMaterial":16.25,"salario":94.78,"costoequipo":0.0,"especialidadesId":"13","costomano":103.39,"subespecialidadesId":"01","nivelId":"01","obraId":214,"id":4848},{"descripcion":"ENCHAPES Y REVESTIMIENTOS","objetosId":"02","codigo":"02","idzona":"001","empresaconstructoraId":"12889","costoMaterial":3898.89,"salario":1458.13,"costoequipo":0.0,"especialidadesId":"13","costomano":1590.79,"subespecialidadesId":"01","nivelId":"01","obraId":214,"id":4846},{"descripcion":"IMPERMEABILIZACIÓN ZONAS HÚMEDAS","objetosId":"02","codigo":"05","idzona":"001","empresaconstructoraId":"12889","costoMaterial":205.70999999999998,"salario":29.4,"costoequipo":0.0,"especialidadesId":"13","costomano":32.07,"subespecialidadesId":"01","nivelId":"01","obraId":214,"id":4849},{"descripcion":"PISOS","objetosId":"02","codigo":"03","idzona":"001","empresaconstructoraId":"12889","costoMaterial":22911.45,"salario":3332.41,"costoequipo":1525.35,"especialidadesId":"13","costomano":3635.45,"subespecialidadesId":"01","nivelId":"02","obraId":214,"id":4853},{"descripcion":"ACCESORIOS SANITARIOS","objetosId":"02","codigo":"04","idzona":"001","empresaconstructoraId":"12889","costoMaterial":16.25,"salario":94.78,"costoequipo":0.0,"especialidadesId":"13","costomano":103.39,"subespecialidadesId":"01","nivelId":"02","obraId":214,"id":4854},{"descripcion":"MUROS","objetosId":"02","codigo":"01","idzona":"001","empresaconstructoraId":"12889","costoMaterial":797.49,"salario":241.41,"costoequipo":0.0,"especialidadesId":"13","costomano":263.38,"subespecialidadesId":"01","nivelId":"04","obraId":214,"id":4857},{"descripcion":"REVESTIMIENTOS","objetosId":"02","codigo":"02","idzona":"001","empresaconstructoraId":"12889","costoMaterial":655.96,"salario":401.03,"costoequipo":0.0,"especialidadesId":"13","costomano":437.51,"subespecialidadesId":"01","nivelId":"04","obraId":214,"id":4858},{"descripcion":"CUBIERTA INCLINADA","objetosId":"02","codigo":"03","idzona":"001","empresaconstructoraId":"12889","costoMaterial":4587.08,"salario":25549.21,"costoequipo":0.0,"especialidadesId":"13","costomano":27873.38,"subespecialidadesId":"01","nivelId":"04","obraId":214,"id":4859},{"descripcion":"CUBIERTA PLANA EN CAJA DE ESCALERA","objetosId":"02","codigo":"04","idzona":"001","empresaconstructoraId":"12889","costoMaterial":1093.08,"salario":2265.72,"costoequipo":83.53,"especialidadesId":"13","costomano":2471.84,"subespecialidadesId":"01","nivelId":"04","obraId":214,"id":4860},{"descripcion":"SOLUCIÓN DE DRENAJE PLUVIAL DE CUBIERTA","objetosId":"02","codigo":"05","idzona":"001","empresaconstructoraId":"12889","costoMaterial":0.16999999999999998,"salario":14.35,"costoequipo":0.0,"especialidadesId":"13","costomano":15.66,"subespecialidadesId":"01","nivelId":"04","obraId":214,"id":4861},{"descripcion":"ESCALERA METÁLICA","objetosId":"02","codigo":"06","idzona":"001","empresaconstructoraId":"12889","costoMaterial":243.51000000000002,"salario":25.75,"costoequipo":44.22,"especialidadesId":"13","costomano":28.09,"subespecialidadesId":"01","nivelId":"04","obraId":214,"id":4862},{"descripcion":"SALIDA DE AZOTEA","objetosId":"02","codigo":"07","idzona":"001","empresaconstructoraId":"12889","costoMaterial":222.59,"salario":48.97,"costoequipo":0.0,"especialidadesId":"13","costomano":53.43,"subespecialidadesId":"01","nivelId":"04","obraId":214,"id":4863},{"descripcion":"MESETAS IN SITU","objetosId":"02","codigo":"12","idzona":"001","empresaconstructoraId":"12889","costoMaterial":629.3,"salario":85.36,"costoequipo":2.0,"especialidadesId":"15","costomano":93.12,"subespecialidadesId":"02","nivelId":"01","obraId":214,"id":4880},{"descripcion":"CARPINTERÍA DE ALUMINIO","objetosId":"02","codigo":"01","idzona":"001","empresaconstructoraId":"12889","costoMaterial":48052.66,"salario":2476.17,"costoequipo":0.0,"especialidadesId":"13","costomano":2701.1,"subespecialidadesId":"01","nivelId":"05","obraId":214,"id":4864},{"descripcion":"BARANDAS","objetosId":"02","codigo":"02","idzona":"001","empresaconstructoraId":"12889","costoMaterial":2745.06,"salario":285.57,"costoequipo":0.0,"especialidadesId":"13","costomano":311.55,"subespecialidadesId":"01","nivelId":"05","obraId":214,"id":4865},{"descripcion":"CONDUCTORES","objetosId":"02","codigo":"06","idzona":"001","empresaconstructoraId":"12889","costoMaterial":195.5,"salario":241.59,"costoequipo":0.0,"especialidadesId":"14","costomano":263.57,"subespecialidadesId":"01","nivelId":"01","obraId":214,"id":4886},{"descripcion":"PINTURAS","objetosId":"02","codigo":"03","idzona":"001","empresaconstructoraId":"12889","costoMaterial":7702.01,"salario":5214.4,"costoequipo":0.0,"especialidadesId":"13","costomano":5687.92,"subespecialidadesId":"01","nivelId":"05","obraId":214,"id":4866},{"descripcion":"PIZARRA ELÉCTRICA","objetosId":"02","codigo":"07","idzona":"001","empresaconstructoraId":"12889","costoMaterial":87.21000000000001,"salario":331.5,"costoequipo":0.0,"especialidadesId":"14","costomano":361.66,"subespecialidadesId":"01","nivelId":"01","obraId":214,"id":4887},{"descripcion":"ENCHAPES Y REVESTIMIENTOS","objetosId":"02","codigo":"04","idzona":"001","empresaconstructoraId":"12889","costoMaterial":8066.68,"salario":994.27,"costoequipo":0.0,"especialidadesId":"13","costomano":1084.72,"subespecialidadesId":"01","nivelId":"05","obraId":214,"id":4867},{"descripcion":"PILASTRAS","objetosId":"02","codigo":"02","idzona":"001","empresaconstructoraId":"12889","costoMaterial":2564.04,"salario":283.48,"costoequipo":3.9,"especialidadesId":"15","costomano":309.23,"subespecialidadesId":"02","nivelId":"01","obraId":214,"id":4870},{"descripcion":"TUBERÍAS Y ACCESORIOS","objetosId":"02","codigo":"01","idzona":"001","empresaconstructoraId":"12889","costoMaterial":442.40999999999997,"salario":186.77,"costoequipo":0.0,"especialidadesId":"16","costomano":203.76,"subespecialidadesId":"01","nivelId":"01","obraId":214,"id":4888},{"descripcion":"DINTELES","objetosId":"02","codigo":"03","idzona":"001","empresaconstructoraId":"12889","costoMaterial":232.92,"salario":58.86,"costoequipo":1.14,"especialidadesId":"15","costomano":64.21,"subespecialidadesId":"02","nivelId":"01","obraId":214,"id":4871},{"descripcion":"TUBERÍAS Y ACCESORIOS","objetosId":"02","codigo":"01","idzona":"001","empresaconstructoraId":"12889","costoMaterial":117.46000000000001,"salario":133.27,"costoequipo":0.0,"especialidadesId":"16","costomano":145.4,"subespecialidadesId":"02","nivelId":"01","obraId":214,"id":4889},{"descripcion":"CERRAMENTOS","objetosId":"02","codigo":"04","idzona":"001","empresaconstructoraId":"12889","costoMaterial":1802.98,"salario":407.29,"costoequipo":8.84,"especialidadesId":"15","costomano":444.31,"subespecialidadesId":"02","nivelId":"01","obraId":214,"id":4872},{"descripcion":"VIGAS","objetosId":"02","codigo":"06","idzona":"001","empresaconstructoraId":"12889","costoMaterial":456.77,"salario":100.68,"costoequipo":2.6,"especialidadesId":"15","costomano":109.83,"subespecialidadesId":"02","nivelId":"01","obraId":214,"id":4874},{"descripcion":"LOSA DE HORMIGÓN FUNDIDA IN SITU EN ENTREPISO","objetosId":"02","codigo":"07","idzona":"001","empresaconstructoraId":"12889","costoMaterial":789.44,"salario":71.38,"costoequipo":2.56,"especialidadesId":"15","costomano":77.87,"subespecialidadesId":"02","nivelId":"01","obraId":214,"id":4875},{"descripcion":"LOSAS PREFABRICADAS","objetosId":"02","codigo":"09","idzona":"001","empresaconstructoraId":"12889","costoMaterial":0.0,"salario":194.1,"costoequipo":578.23,"especialidadesId":"15","costomano":211.7,"subespecialidadesId":"02","nivelId":"01","obraId":214,"id":4877},{"descripcion":"JUNTA ENTRE PANELES","objetosId":"02","codigo":"10","idzona":"001","empresaconstructoraId":"12889","costoMaterial":2372.46,"salario":768.14,"costoequipo":1341.52,"especialidadesId":"15","costomano":838.0,"subespecialidadesId":"02","nivelId":"01","obraId":214,"id":4878},{"descripcion":"ARME Y DESARME DE ANDAMIOS","objetosId":"02","codigo":"05","idzona":"001","empresaconstructoraId":"12889","costoMaterial":0.0,"salario":9637.34,"costoequipo":0.0,"especialidadesId":"13","costomano":10512.81,"subespecialidadesId":"01","nivelId":"05","obraId":214,"id":4868},{"descripcion":"COLUMNAS","objetosId":"02","codigo":"01","idzona":"001","empresaconstructoraId":"12889","costoMaterial":1812.28,"salario":227.95,"costoequipo":8.06,"especialidadesId":"15","costomano":248.67,"subespecialidadesId":"02","nivelId":"01","obraId":214,"id":4869},{"descripcion":"LOSA DE HORMIGÓN FUNDIDA IN SITU PARA CLOSET","objetosId":"02","codigo":"05","idzona":"001","empresaconstructoraId":"12889","costoMaterial":813.43,"salario":118.14,"costoequipo":3.6,"especialidadesId":"15","costomano":128.88,"subespecialidadesId":"02","nivelId":"01","obraId":214,"id":4873},{"descripcion":"JUNTAS ENTRE LOSAS","objetosId":"02","codigo":"08","idzona":"001","empresaconstructoraId":"12889","costoMaterial":377.98,"salario":168.91,"costoequipo":150.19,"especialidadesId":"15","costomano":184.28,"subespecialidadesId":"02","nivelId":"01","obraId":214,"id":4876},{"descripcion":"PANELES PREFABRICADOS","objetosId":"02","codigo":"11","idzona":"001","empresaconstructoraId":"12889","costoMaterial":10.06,"salario":335.72,"costoequipo":1124.71,"especialidadesId":"15","costomano":366.2,"subespecialidadesId":"02","nivelId":"01","obraId":214,"id":4879},{"descripcion":"LUMINARIAS","objetosId":"02","codigo":"01","idzona":"001","empresaconstructoraId":"12889","costoMaterial":722.23,"salario":143.25,"costoequipo":0.0,"especialidadesId":"14","costomano":156.27,"subespecialidadesId":"01","nivelId":"01","obraId":214,"id":4881},{"descripcion":"INTERRUPTORES","objetosId":"02","codigo":"02","idzona":"001","empresaconstructoraId":"12889","costoMaterial":20.040000000000003,"salario":39.79,"costoequipo":0.0,"especialidadesId":"14","costomano":43.41,"subespecialidadesId":"01","nivelId":"01","obraId":214,"id":4882},{"descripcion":"TOMACORRIENTES","objetosId":"02","codigo":"03","idzona":"001","empresaconstructoraId":"12889","costoMaterial":15.32,"salario":23.88,"costoequipo":0.0,"especialidadesId":"14","costomano":26.04,"subespecialidadesId":"01","nivelId":"01","obraId":214,"id":4883},{"descripcion":"TUBERÍAS Y ACCESORIOS","objetosId":"02","codigo":"05","idzona":"001","empresaconstructoraId":"12889","costoMaterial":1151.1,"salario":430.8,"costoequipo":0.0,"especialidadesId":"14","costomano":469.95,"subespecialidadesId":"01","nivelId":"01","obraId":214,"id":4885},{"descripcion":"CAJAS ELÉCTRICAS","objetosId":"02","codigo":"04","idzona":"001","empresaconstructoraId":"12889","costoMaterial":530.58,"salario":640.68,"costoequipo":0.0,"especialidadesId":"14","costomano":698.94,"subespecialidadesId":"01","nivelId":"01","obraId":214,"id":4884}],"niveles":[{"code":"01","ido":756,"id":1109,"desc":"?NICO"},{"code":"01","ido":757,"id":1110,"desc":"PRIMER NIVEL"},{"code":"02","ido":757,"id":1111,"desc":"SEGUNDO NIVEL"},{"code":"03","ido":757,"id":1112,"desc":"TERCER NIVEL"},{"code":"04","ido":757,"id":1113,"desc":"CUBIERTA"},{"code":"05","ido":757,"id":1114,"desc":"GENERAL"}],"coeficientes":[],"id":214,"brigadas":[],"objetos":[{"code":"01","id":756,"idz":229,"desc":"ACT. 1001 PLAN GENERAL"},{"code":"02","id":757,"idz":229,"desc":"ACT. 1003 EDIFICIO TRIPLANTA"}]}